pretix_covid_certificates/__init__.py
pretix_covid_certificates/apps.py
pretix_covid_certificates/models.py
pretix_covid_certificates/signals.py
pretix_covid_certificates/urls.py
pretix_covid_certificates/views.py
pretix_covid_certificates/locale/django.pot
pretix_covid_certificates/locale/de/LC_MESSAGES/django.mo
pretix_covid_certificates/locale/de/LC_MESSAGES/django.po
pretix_covid_certificates/locale/de_Informal/.gitkeep
pretix_covid_certificates/locale/de_Informal/LC_MESSAGES/django.mo
pretix_covid_certificates/locale/de_Informal/LC_MESSAGES/django.po
pretix_covid_certificates/migrations/0001_initial.py
pretix_covid_certificates/migrations/__init__.py
pretix_covid_certificates/static/pretix_covid_certificates/.gitkeep
pretix_covid_certificates/templates/pretix_covid_certificates/.gitkeep
pretix_covid_certificates/templates/pretix_covid_certificates/settings.html
pretix_covid_certificates-2.3.1.dist-info/LICENSE
pretix_covid_certificates-2.3.1.dist-info/METADATA
pretix_covid_certificates-2.3.1.dist-info/WHEEL
pretix_covid_certificates-2.3.1.dist-info/entry_points.txt
pretix_covid_certificates-2.3.1.dist-info/top_level.txt
pretix_covid_certificates-2.3.1.dist-info/RECORD
