Metadata-Version: 2.1
Name: pretix-covid-certificates
Version: 2.3.1
Summary: This plugin allows to configure the validation of COVID test- and vaccination certificates using pretixSCAN for Android
Author-email: pretix team <support@pretix.eu>
Maintainer-email: pretix team <support@pretix.eu>
License: 
Project-URL: homepage, https://github.com/pretix/pretix-covid-certificates
Keywords: pretix
Requires-Python: >=3.9
License-File: LICENSE
